subcmdparse/__init__.py
subcmdparse/subcmdparse.py
subcmdparse/util.py
subcmdparse-0.1.9.dist-info/METADATA
subcmdparse-0.1.9.dist-info/WHEEL
subcmdparse-0.1.9.dist-info/top_level.txt
subcmdparse-0.1.9.dist-info/RECORD
