Metadata-Version: 2.1
Name: subcmdparse
Version: 0.1.9
Summary: Subcommand extension for argparse package
Home-page: https://github.com/dhkim09a/subcmdparse
Author: Donghwi Kim
Author-email: dhkim09@kaist.ac.kr
Requires-Python: >=3.7
Requires-Dist: sh
Provides-Extra: test
Requires-Dist: sh ; extra == 'test'
